exitcodelib.py
exitcodelib-1.2.0.dist-info/METADATA
exitcodelib-1.2.0.dist-info/WHEEL
exitcodelib-1.2.0.dist-info/top_level.txt
exitcodelib-1.2.0.dist-info/RECORD
